pyproject.toml
setup.cfg
./CleanEmonPopulator/EmonPiAdapter.py
./CleanEmonPopulator/__init__.py
./CleanEmonPopulator/__main__.py
./CleanEmonPopulator/buffer.py
./CleanEmonPopulator/service.py
./CleanEmonPopulator/setup/__init__.py
./CleanEmonPopulator/setup/generate_schema.py
./CleanEmonPopulator/tests/__init__.py
./CleanEmonPopulator/tests/test__init__.py
./CleanEmonPopulator/tests/test_buffer.py
./CleanEmonPopulator/tests/test_service.py
CleanEmon_Populator.egg-info/PKG-INFO
CleanEmon_Populator.egg-info/SOURCES.txt
CleanEmon_Populator.egg-info/dependency_links.txt
CleanEmon_Populator.egg-info/entry_points.txt
CleanEmon_Populator.egg-info/requires.txt
CleanEmon_Populator.egg-info/top_level.txt