Metadata-Version: 2.1
Name: CleanEmon-Populator
Version: 0.4
Summary: A package providing utilities for populating the database in CleanEmon ecosystem
Author: George Vasiliadis
Author-email: geor.vasiliadis@gmail.com
Requires-Python: >=3.6
